FastDatasets/app.py
app/__init__.py
app/main.py
app/api/__init__.py
app/api/dataset.py
app/core/__init__.py
app/core/config.py
app/core/dataset.py
app/core/document.py
app/core/llm.py
app/core/logger.py
app/core/prompt.py
app/core/storage.py
app/services/__init__.py
app/services/dataset_service.py
app/utils/__init__.py
fastdatasets/__init__.py
fastdatasets/api.py
fastdatasets/cli.py
fastdatasets_llm-0.1.3.dist-info/licenses/LICENSE
scripts/dataset_generator.py
scripts/distill_dataset.py
scripts/sample_high_quality.py
scripts/test_document.py
scripts/test_llm.py
fastdatasets_llm-0.1.3.dist-info/METADATA
fastdatasets_llm-0.1.3.dist-info/WHEEL
fastdatasets_llm-0.1.3.dist-info/entry_points.txt
fastdatasets_llm-0.1.3.dist-info/top_level.txt
fastdatasets_llm-0.1.3.dist-info/RECORD
