Metadata-Version: 2.4
Name: fastdatasets-llm
Version: 0.1.3
Summary: Generate high-quality LLM training datasets from documents with distillation and augmentation.
Author: FastDatasets Authors
License: Apache-2.0
Project-URL: Homepage, https://github.com/ZhuLinsen/FastDatasets
Project-URL: Repository, https://github.com/ZhuLinsen/FastDatasets
Project-URL: Issues, https://github.com/ZhuLinsen/FastDatasets/issues
Project-URL: Demo, https://huggingface.co/spaces/mumu157/FastDatasets
Keywords: llm,dataset,alpaca,sharegpt,distillation,sft
Classifier: License :: OSI Approved :: Apache Software License
Classifier: Programming Language :: Python :: 3
Classifier: Programming Language :: Python :: 3 :: Only
Classifier: Programming Language :: Python :: 3.8
Classifier: Programming Language :: Python :: 3.9
Classifier: Programming Language :: Python :: 3.10
Classifier: Programming Language :: Python :: 3.11
Classifier: Programming Language :: Python :: 3.12
Classifier: Operating System :: OS Independent
Classifier: Topic :: Scientific/Engineering :: Artificial Intelligence
Requires-Python: >=3.8
License-File: LICENSE
Requires-Dist: pydantic<3,>=2.7.0
Requires-Dist: python-dotenv>=1.0.0
Requires-Dist: loguru>=0.7.0
Requires-Dist: openai>=1.0.0
Requires-Dist: rich>=13.0.0
Requires-Dist: tqdm>=4.65.0
Requires-Dist: httpx>=0.24.0
Provides-Extra: web
Requires-Dist: fastapi>=0.111; extra == "web"
Requires-Dist: uvicorn>=0.30; extra == "web"
Requires-Dist: gradio==4.44.0; extra == "web"
Provides-Extra: doc
Requires-Dist: textract-py3>=2.1.1; extra == "doc"
Provides-Extra: all
Requires-Dist: fastdatasets[web]; extra == "all"
Requires-Dist: fastdatasets[doc]; extra == "all"
Dynamic: license-file
